slurm_viewer/__init__.py
slurm_viewer/__main__.py
slurm_viewer/app.py
slurm_viewer/data/__init__.py
slurm_viewer/data/common_types.py
slurm_viewer/data/config.py
slurm_viewer/data/job_model.py
slurm_viewer/data/job_model_v2.py
slurm_viewer/data/legacy_text_output_tools.py
slurm_viewer/data/models.py
slurm_viewer/data/node_model.py
slurm_viewer/data/partitions_model.py
slurm_viewer/data/priority_model.py
slurm_viewer/data/queue_model.py
slurm_viewer/data/slurm_communication.py
slurm_viewer/data/slurm_protocol.py
slurm_viewer/widgets/__init__.py
slurm_viewer/widgets/loading.py
slurm_viewer/widgets/logo.py
slurm_viewer/widgets/nodes_widget.py
slurm_viewer/widgets/plot_widget.py
slurm_viewer/widgets/priority_widget.py
slurm_viewer/widgets/queue_widget.py
slurm_viewer/widgets/slurm_viewer.tcss
slurm_viewer/widgets/status_widget.py
slurm_viewer/widgets/table_formatting.py
slurm_viewer/widgets/widget_types.py
slurm_viewer/widgets/screens/__init__.py
slurm_viewer/widgets/screens/detail_screen.py
slurm_viewer/widgets/screens/help_gpu.md
slurm_viewer/widgets/screens/help_jobs.md
slurm_viewer/widgets/screens/help_nodes.md
slurm_viewer/widgets/screens/help_screen.py
slurm_viewer/widgets/screens/select_columns_screen.py
slurm_viewer/widgets/screens/select_partitions_screen.py
slurm_viewer-1.0.4.dist-info/licenses/LICENSE
slurm_viewer-1.0.4.dist-info/METADATA
slurm_viewer-1.0.4.dist-info/WHEEL
slurm_viewer-1.0.4.dist-info/entry_points.txt
slurm_viewer-1.0.4.dist-info/top_level.txt
slurm_viewer-1.0.4.dist-info/RECORD
