Metadata-Version: 2.4
Name: slurm-viewer
Version: 1.0.4
Summary: View a SLURM cluster and inspect nodes and jobs.
Author-email: Patrick de Koning <pjhdekoning@lumc.nl>, Prerak Mody <prerakmody@gmail.com>
Project-URL: Homepage, https://lkeb.nl
Project-URL: Repository, https://gitlab.com/lkeb/slurm_viewer
Project-URL: Issues, https://gitlab.com/lkeb/slurm_viewer/issues
Project-URL: Changelog, https://gitlab.com/lkeb/slurm_viewer/blob/master/CHANGELOG.md
Keywords: SLURM,TUI
Classifier: Operating System :: OS Independent
Classifier: Development Status :: 4 - Beta
Classifier: Intended Audience :: Information Technology
Classifier: Intended Audience :: Science/Research
Classifier: License :: OSI Approved :: MIT License
Classifier: Natural Language :: English
Classifier: Programming Language :: Python :: 3.9
Classifier: Environment :: Console
Classifier: Framework :: Pydantic
Classifier: Topic :: Scientific/Engineering
Classifier: Typing :: Typed
Requires-Python: >=3.9
License-File: LICENSE
Requires-Dist: asyncssh>=2.19.0
Requires-Dist: eval_type_backport; python_version < "3.10"
Requires-Dist: importlib-metadata>=8.5.0
Requires-Dist: loguru
Requires-Dist: pydantic>=2.10.4
Requires-Dist: python-dateutil>=2.9.0
Requires-Dist: textual-plotext>=1.0.1
Requires-Dist: textual-sortable-datatable>=0.0.6
Requires-Dist: textual>=3.0.0
Requires-Dist: tomlkit>=0.13.2
Provides-Extra: dev
Requires-Dist: pytest; extra == "dev"
Requires-Dist: pytest-cov; extra == "dev"
Requires-Dist: pytest-asyncio; extra == "dev"
Requires-Dist: pytest-textual-snapshot; extra == "dev"
Requires-Dist: pylint; extra == "dev"
Requires-Dist: pylint-pydantic; extra == "dev"
Requires-Dist: mypy; extra == "dev"
Requires-Dist: textual-dev; extra == "dev"
Requires-Dist: types-python-dateutil; extra == "dev"
Requires-Dist: setuptools-git-versioning; extra == "dev"
Dynamic: license-file
